ecommerce_api_wrapper/__init__.py
ecommerce_api_wrapper/__version__.py
ecommerce_api_wrapper/ecommerce_api_wrapper.py
ecommerce_api_wrapper/providers/__init__.py
ecommerce_api_wrapper/providers/lazada_api_wrapper/__init__.py
ecommerce_api_wrapper/providers/lazada_api_wrapper/constants.py
ecommerce_api_wrapper/providers/lazada_api_wrapper/lazada.py
ecommerce_api_wrapper/providers/lazada_api_wrapper/schemas/__init__.py
ecommerce_api_wrapper/providers/lazada_api_wrapper/schemas/product_schema.py
ecommerce_api_wrapper/providers/lazada_api_wrapper/schemas/response_schema.py
ecommerce_api_wrapper/providers/tokopedia_api_wrapper/__init__.py
ecommerce_api_wrapper/providers/tokopedia_api_wrapper/constants.py
ecommerce_api_wrapper/providers/tokopedia_api_wrapper/tokopedia.py
ecommerce_api_wrapper/providers/tokopedia_api_wrapper/schemas/__init__.py
ecommerce_api_wrapper/providers/tokopedia_api_wrapper/schemas/product_schema.py
ecommerce_api_wrapper/providers/tokopedia_api_wrapper/schemas/response_schema.py
ecommerce_api_wrapper/providers/tokopedia_api_wrapper/utils/__init__.py
ecommerce_api_wrapper/providers/tokopedia_api_wrapper/utils/faker.py
ecommerce_api_wrapper/utils/__init__.py
ecommerce_api_wrapper/utils/faker.py
ecommerce_api_wrapper/utils/transform.py
ecommerce_api_wrapper-0.0.4.dist-info/licenses/LICENSE
ecommerce_api_wrapper-0.0.4.dist-info/METADATA
ecommerce_api_wrapper-0.0.4.dist-info/WHEEL
ecommerce_api_wrapper-0.0.4.dist-info/top_level.txt
ecommerce_api_wrapper-0.0.4.dist-info/RECORD
