Metadata-Version: 2.4
Name: ecommerce-api-wrapper
Version: 0.0.4
Summary: E-commerce Python API Wrapper SDK.
Home-page: https://github.com/fuongz/ecommerce-api-wrapper
Author: fuongz
Author-email: hi@phuongphung.com
License: MIT
Project-URL: Bug Reports, https://github.com/fuongz/ecommerce-api-wrapper/issues
Project-URL: Source, https://github.com/fuongz/ecommerce-api-wrapper
Classifier: Development Status :: 4 - Beta
Classifier: Intended Audience :: Developers
Classifier: Operating System :: OS Independent
Classifier: License :: OSI Approved :: MIT License
Classifier: Programming Language :: Python :: 3.8
Classifier: Programming Language :: Python :: 3.9
Classifier: Programming Language :: Python :: 3.10
Classifier: Programming Language :: Python :: 3.11
Requires-Python: >=3.8, <4
License-File: LICENSE
Requires-Dist: marshmallow==4.0.0
Requires-Dist: requests==2.32.3
Requires-Dist: tqdm==4.67.1
Requires-Dist: urllib3==2.4.0
Dynamic: author
Dynamic: author-email
Dynamic: classifier
Dynamic: description
Dynamic: description-content-type
Dynamic: home-page
Dynamic: keywords
Dynamic: license
Dynamic: license-file
Dynamic: project-url
Dynamic: requires-dist
Dynamic: requires-python
Dynamic: summary
